{
  "kind": "collectionType",
  "collectionName": "fixtures",
  "info": {
    "singularName": "fixture",
    "pluralName": "fixtures",
    "displayName": "fixture"
  },
  "options": {
    "draftAndPublish": true
  },
  "pluginOptions": {},
  "attributes": {
    "home_team": {
      "type": "string",
      "required": true,
      "default": "CCCUL Dublanc FC"
    },
    "away_team": {
      "type": "string",
      "required": true
    },
    "match_date": {
      "type": "datetime",
      "required": true
    },
    "home_team_score": {
      "type": "integer"
    },
    "away_team_score": {
      "type": "integer"
    },
    "Venue": {
      "type": "enumeration",
      "enum": [
        "Stock Farm Technical Center",
        "Almond Park",
        "Benjamin's Park",
        "Laplaine Playing Field",
        "Stadium"
      ],
      "required": true
    }
  }
}
